Metadata-Version: 1.0
Name: Cubic-solver
Version: 0.1
Summary: Get roots of cubic function and plot it
Home-page: UNKNOWN
Author: UNKNOWN
Author-email: UNKNOWN
License: UNKNOWN
Platform: UNKNOWN
